treeshaker/__init__.py
treeshaker/_version.py
treeshaker/config.py
treeshaker/doc_utils.py
treeshaker/pypi_names.py
treeshaker/pypi_names.txt
treeshaker/setup_utils.py
treeshaker/treeshaker.py
treeshaker-0.0.3.dist-info/LICENSE
treeshaker-0.0.3.dist-info/METADATA
treeshaker-0.0.3.dist-info/WHEEL
treeshaker-0.0.3.dist-info/entry_points.txt
treeshaker-0.0.3.dist-info/top_level.txt
treeshaker-0.0.3.dist-info/RECORD
