Metadata-Version: 2.1
Name: treeshaker
Version: 0.0.3
Summary: A tree-shaking tool for Python.
Home-page: https://github.com/sclabs/treeshaker
Author: Thomas Gilgenast
Author-email: thomasgilgenast@gmail.com
License: UNKNOWN
Keywords: tree-shaking
Platform: UNKNOWN
Classifier: Development Status :: 3 - Alpha
Classifier: Environment :: Console
Classifier: Intended Audience :: Developers
Classifier: Programming Language :: Python :: 2
Classifier: Programming Language :: Python :: 2.7
Classifier: Programming Language :: Python :: 3
Classifier: Programming Language :: Python :: 3.6
Classifier: Operating System :: OS Independent
Classifier: Topic :: Software Development
Classifier: Topic :: Software Development :: Build Tools
Classifier: Topic :: System :: Archiving :: Packaging
Classifier: Topic :: System :: Software Distribution
Classifier: License :: OSI Approved :: MIT License
Requires-Dist: fire (>=0.2.1)
Requires-Dist: modulegraph (>=0.18)
Requires-Dist: pip-tools (>=4.5.0)
Requires-Dist: requirements-parser (>=0.2.0)
Requires-Dist: six (>=1.14.0)
Requires-Dist: configparser (>=4.0.2) ; python_version < "3.2"
Requires-Dist: enum34 (>=1.1.9) ; python_version < "3.4"
Requires-Dist: importlib-metadata (>=1.5.0) ; python_version < "3.8"
